svg_path_transform/__init__.py
svg_path_transform/__main__.py
svg_path_transform/__version__.py
svg_path_transform/_cli.py
svg_path_transform/_morph.py
svg_path_transform/_parser.py
svg_path_transform/_segmentize.py
svg_path_transform/_translate_and_scale.py
svg_path_transform/path.lark
svg_path_transform-2.0.2.dist-info/LICENSE
svg_path_transform-2.0.2.dist-info/METADATA
svg_path_transform-2.0.2.dist-info/WHEEL
svg_path_transform-2.0.2.dist-info/entry_points.txt
svg_path_transform-2.0.2.dist-info/top_level.txt
svg_path_transform-2.0.2.dist-info/RECORD
