Metadata-Version: 2.1
Name: svg-path-transform
Version: 2.0.2
Summary: SVG path data transformation toolkit
Home-page: https://github.com/igrmk/svg_path_transform
Author: igrmk
Author-email: igrmkx@gmail.com
License: UNKNOWN
Platform: UNKNOWN
Classifier: Programming Language :: Python :: 3
Classifier: License :: OSI Approved :: MIT License
Classifier: Operating System :: OS Independent
Requires-Python: >=3.6
License-File: LICENSE
Requires-Dist: lark>=0.11.3
Requires-Dist: importlib-metadata; python_version < "3.8"
Provides-Extra: testing
Requires-Dist: pytest; extra == "testing"
